odt2md/__init__.py
odt2md/block.py
odt2md/emphasis.py
odt2md/odt2md.py
odt2md/show_styles.py
odt2md/style.py
odt2md/styler.py
odt2md/util.py
odt2md/resources/profile.py
odt2md-0.1.5.dist-info/METADATA
odt2md-0.1.5.dist-info/WHEEL
odt2md-0.1.5.dist-info/entry_points.txt
odt2md-0.1.5.dist-info/top_level.txt
odt2md-0.1.5.dist-info/RECORD
