Metadata-Version: 2.2
Name: odt2md
Version: 0.1.5
Summary: Tools to convert LibreOffice document to Church-Slavonic Markdown flavor
Author-email: Mike Kroutikov <pgmmpk@gmail.com>
Maintainer-email: Mike Kroutikov <pgmmpk@gmail.com>
License: MIT
Project-URL: Homepage, https://github.com/slavonic/odt2md/
Project-URL: Source, https://github.com/slavonic/odt2md
Keywords: odt,LibreOffice,markdown
Classifier: Development Status :: 4 - Beta
Classifier: Intended Audience :: Developers
Classifier: Intended Audience :: Education
Classifier: Intended Audience :: Religion
Classifier: Intended Audience :: Science/Research
Classifier: License :: OSI Approved :: MIT License
Classifier: Programming Language :: Python :: 3
Classifier: Programming Language :: Python :: 3.9
Classifier: Programming Language :: Python :: 3.10
Classifier: Programming Language :: Python :: 3.11
Classifier: Programming Language :: Python :: 3.12
Classifier: Programming Language :: Python :: 3.13
Classifier: Programming Language :: Python :: 3 :: Only
Requires-Python: >=3.8
Requires-Dist: regex
Requires-Dist: lxml>4.9.1
Requires-Dist: lxmlx
Provides-Extra: dev
Requires-Dist: odt2md; extra == "dev"
Requires-Dist: pytest; extra == "dev"
Requires-Dist: twine; extra == "dev"
